google/cloud/spannerlib/__init__.py
google/cloud/spannerlib/abstract_library_object.py
google/cloud/spannerlib/connection.py
google/cloud/spannerlib/pool.py
google/cloud/spannerlib/rows.py
google/cloud/spannerlib/internal/__init__.py
google/cloud/spannerlib/internal/errors.py
google/cloud/spannerlib/internal/message.py
google/cloud/spannerlib/internal/spannerlib.py
google/cloud/spannerlib/internal/spannerlib_protocol.py
google/cloud/spannerlib/internal/types.py
google/cloud/spannerlib/internal/lib/linux-arm64/spannerlib.h
google/cloud/spannerlib/internal/lib/linux-arm64/spannerlib.so
google/cloud/spannerlib/internal/lib/linux-x64/spannerlib.h
google/cloud/spannerlib/internal/lib/linux-x64/spannerlib.so
google/cloud/spannerlib/internal/lib/osx-arm64/spannerlib.dylib
google/cloud/spannerlib/internal/lib/osx-arm64/spannerlib.h
google/cloud/spannerlib/internal/lib/osx-x64/spannerlib.dylib
google/cloud/spannerlib/internal/lib/osx-x64/spannerlib.h
google/cloud/spannerlib/internal/lib/win-x64/spannerlib.dll
google/cloud/spannerlib/internal/lib/win-x64/spannerlib.h
spannerlib_python-0.1.1.dist-info/licenses/LICENSE
spannerlib_python-0.1.1.dist-info/METADATA
spannerlib_python-0.1.1.dist-info/WHEEL
spannerlib_python-0.1.1.dist-info/top_level.txt
spannerlib_python-0.1.1.dist-info/RECORD
