Metadata-Version: 2.4
Name: spannerlib-python
Version: 0.1.1
Summary: A Python wrapper for the Go spannerlib. This is an internal library that can make breaking changes without prior notice.
Author-email: Google LLC <googleapis-packages@google.com>
License-Expression: Apache-2.0
Project-URL: Homepage, https://github.com/googleapis/go-sql-spanner/tree/main/spannerlib/wrappers/spannerlib-python/spannerlib-python/README.md
Project-URL: Repository, https://github.com/googleapis/go-sql-spanner/tree/main/spannerlib/wrappers/spannerlib-python/spannerlib-python
Classifier: Development Status :: 1 - Planning
Classifier: Intended Audience :: Developers
Classifier: Topic :: Software Development :: Libraries
Classifier: Programming Language :: Python :: 3 :: Only
Classifier: Programming Language :: Python :: 3.10
Classifier: Programming Language :: Python :: 3.11
Classifier: Programming Language :: Python :: 3.12
Classifier: Programming Language :: Python :: 3.13
Classifier: Programming Language :: Python :: 3.14
Requires-Python: >=3.10
License-File: LICENSE
Requires-Dist: google-cloud-spanner
Provides-Extra: dev
Requires-Dist: pytest; extra == "dev"
Requires-Dist: nox; extra == "dev"
Dynamic: license-file
